{"shots": [{"comp": 2, "season": "2003/2004", "match_id": 3749522, "player": "Colin Cameron", "team": "Wolverhampton Wanderers", "minute": 0, "xg": 0.008235074, "goal": 0, "is_pen": false}, {"comp": 2, "season": "2003/2004", "match_id": 3749522, "player": "Thierry Henry", "team": "Arsenal", "minute": 3, "xg": 0.06419814, "goal": 0, "is_pen": false}, {"comp": 2, "season": "2003/2004", "match_id": 3749522, "player": "Thierry Henry", "team": "Arsenal", "minute": 12, "xg": 0.038758975, "goal": 0, "is_pen": false}, {"comp": 2, "season": "2003/2004", "match_id": 3749522, "player": "Fredrik Ljungberg", "team": "Arsenal", "minute": 16, "xg": 0.08716674, "goal": 0, "is_pen": false}, {"comp": 2, "season": "2003/2004", "match_id": 3749522, "player": "Thierry Henry", "team": "Arsenal", "minute": 19, "xg": 0.2081062, "goal": 1, "is_pen": false}, {"comp": 2, "season": "2003/2004", "match_id": 3749522, "player": "Dennis Bergkamp", "team": "Arsenal", "minute": 21, "xg": 0.032242496, "goal": 0, "is_pen": false}, {"comp": 2, "season": "2003/2004", "match_id": 3749522, "player": "Thierry Henry", "team": "Arsenal", "minute": 27, "xg": 0.006921836, "goal": 0, "is_pen": false}, {"comp": 2, "season": "2003/2004", "match_id": 3749522, "player": "Kenny Miller", "team": "Wolverhampton Wanderers", "minute": 32, "xg": 0.26727, "goal": 0, "is_pen": false}, {"comp": 2, "season": "2003/2004", "match_id": 3749522, "player": "Ray Parlour", "team": "Arsenal", "minute": 34, "xg": 0.020648506, "goal": 0, "is_pen": false}, {"comp": 2, "season": "2003/2004", "match_id": 3749522, "player": "Dennis Bergkamp", "team": "Arsenal", "minute": 35, "xg": 0.081988454, "goal": 0, "is_pen": false}, {"comp": 2, "season": "2003/2004", "match_id": 3749522, "player": "Henri Camara", "team": "Wolverhampton Wanderers", "minute": 43, "xg": 0.023858244, "goal": 0, "is_pen": false}, {"comp": 2, "season": "2003/2004", "match_id": 3749522, "player": "Jody Craddock", "team": "Wolverhampton Wanderers", "minute": 43, "xg": 0.19786966, "goal": 0, "is_pen": false}, {"comp": 2, "season": "2003/2004", "match_id": 3749522, "player": "Robert Pir\u00e8s", "team": "Arsenal", "minute": 45, "xg": 0.03428903, "goal": 0, "is_pen": false}, {"comp": 2, "season": "2003/2004", "match_id": 3749522, "player": "Mark Kennedy", "team": "Wolverhampton Wanderers", "minute": 52, "xg": 0.02152702, "goal": 0, "is_pen": false}, {"comp": 2, "season": "2003/2004", "match_id": 3749522, "player": "Dennis Bergkamp", "team": "Arsenal", "minute": 58, "xg": 0.04436357, "goal": 0, "is_pen": false}, {"comp": 2, "season": "2003/2004", "match_id": 3749522, "player": "Sulzeer Jeremiah ''Sol' Campbell", "team": "Arsenal", "minute": 61, "xg": 0.08144611, "goal": 0, "is_pen": false}, {"comp": 2, "season": "2003/2004", "match_id": 3749522, "player": "Sulzeer Jeremiah ''Sol' Campbell", "team": "Arsenal", "minute": 67, "xg": 0.072387226, "goal": 0, "is_pen": false}, {"comp": 2, "season": "2003/2004", "match_id": 3749522, "player": "Paul Ince", "team": "Wolverhampton Wanderers", "minute": 75, "xg": 0.07628197, "goal": 0, "is_pen": false}, {"comp": 2, "season": "2003/2004", "match_id": 3749522, "player": "Dennis Bergkamp", "team": "Arsenal", "minute": 80, "xg": 0.073340915, "goal": 0, "is_pen": false}, {"comp": 2, "season": "2003/2004", "match_id": 3749522, "player": "J\u00e9r\u00e9mie Aliadi\u00e8re", "team": "Arsenal", "minute": 82, "xg": 0.027866354, "goal": 0, "is_pen": false}, {"comp": 2, "season": "2003/2004", "match_id": 3749522, "player": "Eduardo C\u00e9sar Daude Gaspar", "team": "Arsenal", "minute": 85, "xg": 0.032320082, "goal": 0, "is_pen": false}, {"comp": 2, "season": "2003/2004", "match_id": 3749522, "player": "Thierry Henry", "team": "Arsenal", "minute": 88, "xg": 0.10623155, "goal": 1, "is_pen": false}, {"comp": 2, "season": "2003/2004", "match_id": 3749522, "player": "Lee Naylor", "team": "Wolverhampton Wanderers", "minute": 90, "xg": 0.011188577, "goal": 0, "is_pen": false}], "assists": []}