{"shots": [{"comp": 55, "season": "2020", "match_id": 3788744, "player": "Kevin Mbabu", "team": "Switzerland", "minute": 5, "xg": 0.026312254, "goal": 0, "is_pen": false}, {"comp": 55, "season": "2020", "match_id": 3788744, "player": "Granit Xhaka", "team": "Switzerland", "minute": 10, "xg": 0.017772896, "goal": 0, "is_pen": false}, {"comp": 55, "season": "2020", "match_id": 3788744, "player": "Kieffer Roberto Francisco Moore", "team": "Wales", "minute": 14, "xg": 0.07550494, "goal": 0, "is_pen": false}, {"comp": 55, "season": "2020", "match_id": 3788744, "player": "Kieffer Roberto Francisco Moore", "team": "Wales", "minute": 15, "xg": 0.10644428, "goal": 0, "is_pen": false}, {"comp": 55, "season": "2020", "match_id": 3788744, "player": "Fabian Lukas Sch\u00e4r", "team": "Switzerland", "minute": 19, "xg": 0.08005007, "goal": 0, "is_pen": false}, {"comp": 55, "season": "2020", "match_id": 3788744, "player": "Haris Seferovi\u0107", "team": "Switzerland", "minute": 21, "xg": 0.052362066, "goal": 0, "is_pen": false}, {"comp": 55, "season": "2020", "match_id": 3788744, "player": "Granit Xhaka", "team": "Switzerland", "minute": 23, "xg": 0.03150504, "goal": 0, "is_pen": false}, {"comp": 55, "season": "2020", "match_id": 3788744, "player": "Haris Seferovi\u0107", "team": "Switzerland", "minute": 26, "xg": 0.110931315, "goal": 0, "is_pen": false}, {"comp": 55, "season": "2020", "match_id": 3788744, "player": "Manuel Obafemi Akanji", "team": "Switzerland", "minute": 33, "xg": 0.07983221, "goal": 0, "is_pen": false}, {"comp": 55, "season": "2020", "match_id": 3788744, "player": "Breel-Donald Embolo", "team": "Switzerland", "minute": 35, "xg": 0.022253238, "goal": 0, "is_pen": false}, {"comp": 55, "season": "2020", "match_id": 3788744, "player": "Haris Seferovi\u0107", "team": "Switzerland", "minute": 40, "xg": 0.06265817, "goal": 0, "is_pen": false}, {"comp": 55, "season": "2020", "match_id": 3788744, "player": "Fabian Lukas Sch\u00e4r", "team": "Switzerland", "minute": 44, "xg": 0.051866136, "goal": 0, "is_pen": false}, {"comp": 55, "season": "2020", "match_id": 3788744, "player": "Haris Seferovi\u0107", "team": "Switzerland", "minute": 45, "xg": 0.26858392, "goal": 0, "is_pen": false}, {"comp": 55, "season": "2020", "match_id": 3788744, "player": "Breel-Donald Embolo", "team": "Switzerland", "minute": 45, "xg": 0.03311858, "goal": 0, "is_pen": false}, {"comp": 55, "season": "2020", "match_id": 3788744, "player": "Breel-Donald Embolo", "team": "Switzerland", "minute": 48, "xg": 0.32462785, "goal": 0, "is_pen": false}, {"comp": 55, "season": "2020", "match_id": 3788744, "player": "Breel-Donald Embolo", "team": "Switzerland", "minute": 48, "xg": 0.08820172, "goal": 1, "is_pen": false}, {"comp": 55, "season": "2020", "match_id": 3788744, "player": "Kevin Mbabu", "team": "Switzerland", "minute": 51, "xg": 0.10633996, "goal": 0, "is_pen": false}, {"comp": 55, "season": "2020", "match_id": 3788744, "player": "Daniel James", "team": "Wales", "minute": 56, "xg": 0.100927465, "goal": 0, "is_pen": false}, {"comp": 55, "season": "2020", "match_id": 3788744, "player": "Connor Roberts", "team": "Wales", "minute": 57, "xg": 0.038612284, "goal": 0, "is_pen": false}, {"comp": 55, "season": "2020", "match_id": 3788744, "player": "Ben Davies", "team": "Wales", "minute": 60, "xg": 0.053992726, "goal": 0, "is_pen": false}, {"comp": 55, "season": "2020", "match_id": 3788744, "player": "Breel-Donald Embolo", "team": "Switzerland", "minute": 64, "xg": 0.03198269, "goal": 0, "is_pen": false}, {"comp": 55, "season": "2020", "match_id": 3788744, "player": "Kieffer Roberto Francisco Moore", "team": "Wales", "minute": 73, "xg": 0.08625654, "goal": 1, "is_pen": false}, {"comp": 55, "season": "2020", "match_id": 3788744, "player": "Ben Davies", "team": "Wales", "minute": 78, "xg": 0.030229198, "goal": 0, "is_pen": false}, {"comp": 55, "season": "2020", "match_id": 3788744, "player": "Denis Lemi Zakaria Lako Lado", "team": "Switzerland", "minute": 80, "xg": 0.04360738, "goal": 0, "is_pen": false}, {"comp": 55, "season": "2020", "match_id": 3788744, "player": "Joseff Morrell", "team": "Wales", "minute": 81, "xg": 0.025420392, "goal": 0, "is_pen": false}, {"comp": 55, "season": "2020", "match_id": 3788744, "player": "Gareth Frank Bale", "team": "Wales", "minute": 88, "xg": 0.058556426, "goal": 0, "is_pen": false}, {"comp": 55, "season": "2020", "match_id": 3788744, "player": "Breel-Donald Embolo", "team": "Switzerland", "minute": 89, "xg": 0.12787202, "goal": 0, "is_pen": false}], "assists": []}