{"shots": [{"comp": 43, "season": "2022", "match_id": 3857294, "player": "Memphis Depay", "team": "Netherlands", "minute": 0, "xg": 0.04113277, "goal": 0, "is_pen": false}, {"comp": 43, "season": "2022", "match_id": 3857294, "player": "Hassan Khalid Al Heidos", "team": "Qatar", "minute": 2, "xg": 0.015712837, "goal": 0, "is_pen": false}, {"comp": 43, "season": "2022", "match_id": 3857294, "player": "Daley Blind", "team": "Netherlands", "minute": 3, "xg": 0.10723932, "goal": 0, "is_pen": false}, {"comp": 43, "season": "2022", "match_id": 3857294, "player": "Daley Blind", "team": "Netherlands", "minute": 3, "xg": 0.042171385, "goal": 0, "is_pen": false}, {"comp": 43, "season": "2022", "match_id": 3857294, "player": "Cody Math\u00e8s Gakpo", "team": "Netherlands", "minute": 6, "xg": 0.023612352, "goal": 0, "is_pen": false}, {"comp": 43, "season": "2022", "match_id": 3857294, "player": "Frenkie de Jong", "team": "Netherlands", "minute": 13, "xg": 0.032602046, "goal": 0, "is_pen": false}, {"comp": 43, "season": "2022", "match_id": 3857294, "player": "Memphis Depay", "team": "Netherlands", "minute": 13, "xg": 0.14338174, "goal": 0, "is_pen": false}, {"comp": 43, "season": "2022", "match_id": 3857294, "player": "Davy Klaassen", "team": "Netherlands", "minute": 18, "xg": 0.08364612, "goal": 0, "is_pen": false}, {"comp": 43, "season": "2022", "match_id": 3857294, "player": "Abdelkarim Hassan Al Haj Fadlalla", "team": "Qatar", "minute": 24, "xg": 0.067132466, "goal": 0, "is_pen": false}, {"comp": 43, "season": "2022", "match_id": 3857294, "player": "Memphis Depay", "team": "Netherlands", "minute": 25, "xg": 0.0753362, "goal": 0, "is_pen": false}, {"comp": 43, "season": "2022", "match_id": 3857294, "player": "Cody Math\u00e8s Gakpo", "team": "Netherlands", "minute": 25, "xg": 0.14035599, "goal": 1, "is_pen": false}, {"comp": 43, "season": "2022", "match_id": 3857294, "player": "Ismaeel Mohammad Mohammad", "team": "Qatar", "minute": 28, "xg": 0.03016361, "goal": 0, "is_pen": false}, {"comp": 43, "season": "2022", "match_id": 3857294, "player": "Memphis Depay", "team": "Netherlands", "minute": 47, "xg": 0.029451067, "goal": 0, "is_pen": false}, {"comp": 43, "season": "2022", "match_id": 3857294, "player": "Memphis Depay", "team": "Netherlands", "minute": 48, "xg": 0.2959347, "goal": 0, "is_pen": false}, {"comp": 43, "season": "2022", "match_id": 3857294, "player": "Frenkie de Jong", "team": "Netherlands", "minute": 48, "xg": 0.6883914, "goal": 1, "is_pen": false}, {"comp": 43, "season": "2022", "match_id": 3857294, "player": "Abdulaziz Hatem Mohammed Abdullah", "team": "Qatar", "minute": 76, "xg": 0.024495702, "goal": 0, "is_pen": false}, {"comp": 43, "season": "2022", "match_id": 3857294, "player": "Pedro Miguel Correia", "team": "Qatar", "minute": 87, "xg": 0.00621196, "goal": 0, "is_pen": false}, {"comp": 43, "season": "2022", "match_id": 3857294, "player": "Steven Berghuis", "team": "Netherlands", "minute": 91, "xg": 0.010698183, "goal": 0, "is_pen": false}], "assists": []}