{"shots": [{"comp": 43, "season": "2022", "match_id": 3857258, "player": "Neymar da Silva Santos Junior", "team": "Brazil", "minute": 12, "xg": 0.00018, "goal": 0, "is_pen": false}, {"comp": 43, "season": "2022", "match_id": 3857258, "player": "Neymar da Silva Santos Junior", "team": "Brazil", "minute": 20, "xg": 0.020173745, "goal": 0, "is_pen": false}, {"comp": 43, "season": "2022", "match_id": 3857258, "player": "Carlos Henrique Casimiro", "team": "Brazil", "minute": 20, "xg": 0.0075366697, "goal": 0, "is_pen": false}, {"comp": 43, "season": "2022", "match_id": 3857258, "player": "Raphael Dias Belloli", "team": "Brazil", "minute": 34, "xg": 0.119197816, "goal": 0, "is_pen": false}, {"comp": 43, "season": "2022", "match_id": 3857258, "player": "Filip Mladenovi\u0107", "team": "Serbia", "minute": 36, "xg": 0.026318645, "goal": 0, "is_pen": false}, {"comp": 43, "season": "2022", "match_id": 3857258, "player": "Vin\u00edcius Jos\u00e9 Paix\u00e3o de Oliveira J\u00fanior", "team": "Brazil", "minute": 40, "xg": 0.09814694, "goal": 0, "is_pen": false}, {"comp": 43, "season": "2022", "match_id": 3857258, "player": "Raphael Dias Belloli", "team": "Brazil", "minute": 45, "xg": 0.4224228, "goal": 0, "is_pen": false}, {"comp": 43, "season": "2022", "match_id": 3857258, "player": "Neymar da Silva Santos Junior", "team": "Brazil", "minute": 49, "xg": 0.06281959, "goal": 0, "is_pen": false}, {"comp": 43, "season": "2022", "match_id": 3857258, "player": "Thiago Emiliano da Silva", "team": "Brazil", "minute": 50, "xg": 0.06673048, "goal": 0, "is_pen": false}, {"comp": 43, "season": "2022", "match_id": 3857258, "player": "Richarlison de Andrade", "team": "Brazil", "minute": 50, "xg": 0.0399856, "goal": 0, "is_pen": false}, {"comp": 43, "season": "2022", "match_id": 3857258, "player": "Danilo Luiz da Silva", "team": "Brazil", "minute": 53, "xg": 0.016877638, "goal": 0, "is_pen": false}, {"comp": 43, "season": "2022", "match_id": 3857258, "player": "Neymar da Silva Santos Junior", "team": "Brazil", "minute": 54, "xg": 0.11246919, "goal": 0, "is_pen": false}, {"comp": 43, "season": "2022", "match_id": 3857258, "player": "Alex Sandro Lobo Silva", "team": "Brazil", "minute": 59, "xg": 0.021819543, "goal": 0, "is_pen": false}, {"comp": 43, "season": "2022", "match_id": 3857258, "player": "Vin\u00edcius Jos\u00e9 Paix\u00e3o de Oliveira J\u00fanior", "team": "Brazil", "minute": 59, "xg": 0.009459062, "goal": 0, "is_pen": false}, {"comp": 43, "season": "2022", "match_id": 3857258, "player": "Vin\u00edcius Jos\u00e9 Paix\u00e3o de Oliveira J\u00fanior", "team": "Brazil", "minute": 61, "xg": 0.07986015, "goal": 0, "is_pen": false}, {"comp": 43, "season": "2022", "match_id": 3857258, "player": "Richarlison de Andrade", "team": "Brazil", "minute": 61, "xg": 0.568145, "goal": 1, "is_pen": false}, {"comp": 43, "season": "2022", "match_id": 3857258, "player": "Vin\u00edcius Jos\u00e9 Paix\u00e3o de Oliveira J\u00fanior", "team": "Brazil", "minute": 66, "xg": 0.14253756, "goal": 0, "is_pen": false}, {"comp": 43, "season": "2022", "match_id": 3857258, "player": "Strahinja Pavlovi\u0107", "team": "Serbia", "minute": 68, "xg": 0.098937765, "goal": 0, "is_pen": false}, {"comp": 43, "season": "2022", "match_id": 3857258, "player": "Darko Lazovi\u0107", "team": "Serbia", "minute": 69, "xg": 0.018288644, "goal": 0, "is_pen": false}, {"comp": 43, "season": "2022", "match_id": 3857258, "player": "Richarlison de Andrade", "team": "Brazil", "minute": 72, "xg": 0.07569885, "goal": 1, "is_pen": false}, {"comp": 43, "season": "2022", "match_id": 3857258, "player": "Carlos Henrique Casimiro", "team": "Brazil", "minute": 76, "xg": 0.010592449, "goal": 0, "is_pen": false}, {"comp": 43, "season": "2022", "match_id": 3857258, "player": "Carlos Henrique Casimiro", "team": "Brazil", "minute": 80, "xg": 0.06218912, "goal": 0, "is_pen": false}, {"comp": 43, "season": "2022", "match_id": 3857258, "player": "Rodrygo Silva de Goes", "team": "Brazil", "minute": 81, "xg": 0.03669105, "goal": 0, "is_pen": false}, {"comp": 43, "season": "2022", "match_id": 3857258, "player": "Frederico Rodrigues Santos", "team": "Brazil", "minute": 82, "xg": 0.088970646, "goal": 0, "is_pen": false}, {"comp": 43, "season": "2022", "match_id": 3857258, "player": "Nikola Milenkovi\u0107", "team": "Serbia", "minute": 84, "xg": 0.011090157, "goal": 0, "is_pen": false}, {"comp": 43, "season": "2022", "match_id": 3857258, "player": "Rodrygo Silva de Goes", "team": "Brazil", "minute": 86, "xg": 0.051727816, "goal": 0, "is_pen": false}, {"comp": 43, "season": "2022", "match_id": 3857258, "player": "Antony Matheus dos Santos", "team": "Brazil", "minute": 87, "xg": 0.009657804, "goal": 0, "is_pen": false}, {"comp": 43, "season": "2022", "match_id": 3857258, "player": "Nemanja Radonji\u0107", "team": "Serbia", "minute": 97, "xg": 0.008691933, "goal": 0, "is_pen": false}], "assists": []}