{"shots": [{"comp": 55, "season": "2024", "match_id": 3942226, "player": "Pedro Gonz\u00e1lez L\u00f3pez", "team": "Spain", "minute": 0, "xg": 0.11743693, "goal": 0, "is_pen": false}, {"comp": 55, "season": "2024", "match_id": 3942226, "player": "Nicholas Williams Arthuer", "team": "Spain", "minute": 11, "xg": 0.021921165, "goal": 0, "is_pen": false}, {"comp": 55, "season": "2024", "match_id": 3942226, "player": "Lamine Yamal Nasraoui Ebana", "team": "Spain", "minute": 14, "xg": 0.084460065, "goal": 0, "is_pen": false}, {"comp": 55, "season": "2024", "match_id": 3942226, "player": "\u00c1lvaro Borja Morata Mart\u00edn", "team": "Spain", "minute": 15, "xg": 0.013587153, "goal": 0, "is_pen": false}, {"comp": 55, "season": "2024", "match_id": 3942226, "player": "Fabi\u00e1n Ruiz Pe\u00f1a", "team": "Spain", "minute": 16, "xg": 0.06860946, "goal": 0, "is_pen": false}, {"comp": 55, "season": "2024", "match_id": 3942226, "player": "Kai Havertz", "team": "Germany", "minute": 20, "xg": 0.07551446, "goal": 0, "is_pen": false}, {"comp": 55, "season": "2024", "match_id": 3942226, "player": "Aymeric Laporte", "team": "Spain", "minute": 22, "xg": 0.020855846, "goal": 0, "is_pen": false}, {"comp": 55, "season": "2024", "match_id": 3942226, "player": "Jonathan Tah", "team": "Germany", "minute": 24, "xg": 0.021546038, "goal": 0, "is_pen": false}, {"comp": 55, "season": "2024", "match_id": 3942226, "player": "Kai Havertz", "team": "Germany", "minute": 34, "xg": 0.154297, "goal": 0, "is_pen": false}, {"comp": 55, "season": "2024", "match_id": 3942226, "player": "Daniel Olmo Carvajal", "team": "Spain", "minute": 38, "xg": 0.029002221, "goal": 0, "is_pen": false}, {"comp": 55, "season": "2024", "match_id": 3942226, "player": "Lamine Yamal Nasraoui Ebana", "team": "Spain", "minute": 44, "xg": 0.027097616, "goal": 0, "is_pen": false}, {"comp": 55, "season": "2024", "match_id": 3942226, "player": "\u00c1lvaro Borja Morata Mart\u00edn", "team": "Spain", "minute": 46, "xg": 0.15766257, "goal": 0, "is_pen": false}, {"comp": 55, "season": "2024", "match_id": 3942226, "player": "Robert Andrich", "team": "Germany", "minute": 47, "xg": 0.020109814, "goal": 0, "is_pen": false}, {"comp": 55, "season": "2024", "match_id": 3942226, "player": "Daniel Olmo Carvajal", "team": "Spain", "minute": 51, "xg": 0.16316466, "goal": 1, "is_pen": false}, {"comp": 55, "season": "2024", "match_id": 3942226, "player": "Jamal Musiala", "team": "Germany", "minute": 54, "xg": 0.040737197, "goal": 0, "is_pen": false}, {"comp": 55, "season": "2024", "match_id": 3942226, "player": "Nicholas Williams Arthuer", "team": "Spain", "minute": 54, "xg": 0.12471274, "goal": 0, "is_pen": false}, {"comp": 55, "season": "2024", "match_id": 3942226, "player": "Florian Wirtz", "team": "Germany", "minute": 59, "xg": 0.028129423, "goal": 0, "is_pen": false}, {"comp": 55, "season": "2024", "match_id": 3942226, "player": "Niclas F\u00fcllkrug", "team": "Germany", "minute": 63, "xg": 0.046607595, "goal": 0, "is_pen": false}, {"comp": 55, "season": "2024", "match_id": 3942226, "player": "Robert Andrich", "team": "Germany", "minute": 69, "xg": 0.06904092, "goal": 0, "is_pen": false}, {"comp": 55, "season": "2024", "match_id": 3942226, "player": "Kai Havertz", "team": "Germany", "minute": 71, "xg": 0.08557191, "goal": 0, "is_pen": false}, {"comp": 55, "season": "2024", "match_id": 3942226, "player": "Niclas F\u00fcllkrug", "team": "Germany", "minute": 71, "xg": 0.078394026, "goal": 0, "is_pen": false}, {"comp": 55, "season": "2024", "match_id": 3942226, "player": "Niclas F\u00fcllkrug", "team": "Germany", "minute": 76, "xg": 0.10089645, "goal": 0, "is_pen": false}, {"comp": 55, "season": "2024", "match_id": 3942226, "player": "Jamal Musiala", "team": "Germany", "minute": 80, "xg": 0.06056656, "goal": 0, "is_pen": false}, {"comp": 55, "season": "2024", "match_id": 3942226, "player": "Kai Havertz", "team": "Germany", "minute": 81, "xg": 0.037947286, "goal": 0, "is_pen": false}, {"comp": 55, "season": "2024", "match_id": 3942226, "player": "Fabi\u00e1n Ruiz Pe\u00f1a", "team": "Spain", "minute": 83, "xg": 0.04979181, "goal": 0, "is_pen": false}, {"comp": 55, "season": "2024", "match_id": 3942226, "player": "Maximilian Mittelst\u00e4dt", "team": "Germany", "minute": 87, "xg": 0.040309463, "goal": 0, "is_pen": false}, {"comp": 55, "season": "2024", "match_id": 3942226, "player": "Florian Wirtz", "team": "Germany", "minute": 88, "xg": 0.119556814, "goal": 1, "is_pen": false}, {"comp": 55, "season": "2024", "match_id": 3942226, "player": "Thomas M\u00fcller", "team": "Germany", "minute": 93, "xg": 0.23735376, "goal": 0, "is_pen": false}, {"comp": 55, "season": "2024", "match_id": 3942226, "player": "Ferr\u00e1n Torres Garc\u00eda", "team": "Spain", "minute": 90, "xg": 0.051860645, "goal": 0, "is_pen": false}, {"comp": 55, "season": "2024", "match_id": 3942226, "player": "Mikel Oyarzabal Ugarte", "team": "Spain", "minute": 94, "xg": 0.026732832, "goal": 0, "is_pen": false}, {"comp": 55, "season": "2024", "match_id": 3942226, "player": "Daniel Olmo Carvajal", "team": "Spain", "minute": 96, "xg": 0.018918002, "goal": 0, "is_pen": false}, {"comp": 55, "season": "2024", "match_id": 3942226, "player": "Robert Andrich", "team": "Germany", "minute": 100, "xg": 0.0269288, "goal": 0, "is_pen": false}, {"comp": 55, "season": "2024", "match_id": 3942226, "player": "Mikel Oyarzabal Ugarte", "team": "Spain", "minute": 103, "xg": 0.022105819, "goal": 0, "is_pen": false}, {"comp": 55, "season": "2024", "match_id": 3942226, "player": "Florian Wirtz", "team": "Germany", "minute": 105, "xg": 0.1075199, "goal": 0, "is_pen": false}, {"comp": 55, "season": "2024", "match_id": 3942226, "player": "Jamal Musiala", "team": "Germany", "minute": 105, "xg": 0.0490711, "goal": 0, "is_pen": false}, {"comp": 55, "season": "2024", "match_id": 3942226, "player": "Niclas F\u00fcllkrug", "team": "Germany", "minute": 108, "xg": 0.045802347, "goal": 0, "is_pen": false}, {"comp": 55, "season": "2024", "match_id": 3942226, "player": "Mikel Oyarzabal Ugarte", "team": "Spain", "minute": 111, "xg": 0.04228213, "goal": 0, "is_pen": false}, {"comp": 55, "season": "2024", "match_id": 3942226, "player": "Niclas F\u00fcllkrug", "team": "Germany", "minute": 116, "xg": 0.052276906, "goal": 0, "is_pen": false}, {"comp": 55, "season": "2024", "match_id": 3942226, "player": "Mikel Merino Zaz\u00f3n", "team": "Spain", "minute": 118, "xg": 0.20066643, "goal": 1, "is_pen": false}, {"comp": 55, "season": "2024", "match_id": 3942226, "player": "Joshua Kimmich", "team": "Germany", "minute": 121, "xg": 0.044950247, "goal": 0, "is_pen": false}, {"comp": 55, "season": "2024", "match_id": 3942226, "player": "Ferr\u00e1n Torres Garc\u00eda", "team": "Spain", "minute": 121, "xg": 0.29318613, "goal": 0, "is_pen": false}, {"comp": 55, "season": "2024", "match_id": 3942226, "player": "Niclas F\u00fcllkrug", "team": "Germany", "minute": 122, "xg": 0.08594657, "goal": 0, "is_pen": false}], "assists": []}