[{"season": "2018/2019", "match_id": 16086, "player": "Borja Iglesias Quintas", "team": "Espanyol", "minute": 8, "xg": 0.1073635, "goal": 0, "is_pen": false}, {"season": "2018/2019", "match_id": 16086, "player": "Lionel Andr\u00e9s Messi Cuccittini", "team": "Barcelona", "minute": 16, "xg": 0.06519264, "goal": 1, "is_pen": false}, {"season": "2018/2019", "match_id": 16086, "player": "Luis Alberto Su\u00e1rez D\u00edaz", "team": "Barcelona", "minute": 20, "xg": 0.16804774, "goal": 0, "is_pen": false}, {"season": "2018/2019", "match_id": 16086, "player": "V\u00edctor S\u00e1nchez Mata", "team": "Espanyol", "minute": 21, "xg": 0.112297356, "goal": 0, "is_pen": false}, {"season": "2018/2019", "match_id": 16086, "player": "Ousmane Demb\u00e9l\u00e9", "team": "Barcelona", "minute": 25, "xg": 0.056286942, "goal": 1, "is_pen": false}, {"season": "2018/2019", "match_id": 16086, "player": "Sergi Darder Moll", "team": "Espanyol", "minute": 27, "xg": 0.02279801, "goal": 0, "is_pen": false}, {"season": "2018/2019", "match_id": 16086, "player": "Hern\u00e1n Arsenio P\u00e9rez Gonz\u00e1lez", "team": "Espanyol", "minute": 30, "xg": 0.039735094, "goal": 0, "is_pen": false}, {"season": "2018/2019", "match_id": 16086, "player": "\u00d3scar Esau Duarte Gait\u00e1n", "team": "Espanyol", "minute": 31, "xg": 0.08245883, "goal": 0, "is_pen": false}, {"season": "2018/2019", "match_id": 16086, "player": "David L\u00f3pez Silva", "team": "Espanyol", "minute": 33, "xg": 0.114816986, "goal": 0, "is_pen": false}, {"season": "2018/2019", "match_id": 16086, "player": "Luis Alberto Su\u00e1rez D\u00edaz", "team": "Barcelona", "minute": 35, "xg": 0.29755476, "goal": 0, "is_pen": false}, {"season": "2018/2019", "match_id": 16086, "player": "Arturo Erasmo Vidal Pardo", "team": "Barcelona", "minute": 35, "xg": 0.18966863, "goal": 0, "is_pen": false}, {"season": "2018/2019", "match_id": 16086, "player": "Jordi Alba Ramos", "team": "Barcelona", "minute": 35, "xg": 0.056373082, "goal": 0, "is_pen": false}, {"season": "2018/2019", "match_id": 16086, "player": "Ivan Rakiti\u0107", "team": "Barcelona", "minute": 36, "xg": 0.24706541, "goal": 0, "is_pen": false}, {"season": "2018/2019", "match_id": 16086, "player": "Lionel Andr\u00e9s Messi Cuccittini", "team": "Barcelona", "minute": 36, "xg": 0.25297776, "goal": 0, "is_pen": false}, {"season": "2018/2019", "match_id": 16086, "player": "Hern\u00e1n Arsenio P\u00e9rez Gonz\u00e1lez", "team": "Espanyol", "minute": 40, "xg": 0.12246964, "goal": 0, "is_pen": false}, {"season": "2018/2019", "match_id": 16086, "player": "Luis Alberto Su\u00e1rez D\u00edaz", "team": "Barcelona", "minute": 44, "xg": 0.014568271, "goal": 1, "is_pen": false}, {"season": "2018/2019", "match_id": 16086, "player": "Sergi Darder Moll", "team": "Espanyol", "minute": 52, "xg": 0.033509202, "goal": 0, "is_pen": false}, {"season": "2018/2019", "match_id": 16086, "player": "Luis Alberto Su\u00e1rez D\u00edaz", "team": "Barcelona", "minute": 55, "xg": 0.030921033, "goal": 0, "is_pen": false}, {"season": "2018/2019", "match_id": 16086, "player": "Ousmane Demb\u00e9l\u00e9", "team": "Barcelona", "minute": 57, "xg": 0.09770712, "goal": 0, "is_pen": false}, {"season": "2018/2019", "match_id": 16086, "player": "Lionel Andr\u00e9s Messi Cuccittini", "team": "Barcelona", "minute": 57, "xg": 0.23628311, "goal": 0, "is_pen": false}, {"season": "2018/2019", "match_id": 16086, "player": "Hern\u00e1n Arsenio P\u00e9rez Gonz\u00e1lez", "team": "Espanyol", "minute": 57, "xg": 0.083256885, "goal": 0, "is_pen": false}, {"season": "2018/2019", "match_id": 16086, "player": "Lionel Andr\u00e9s Messi Cuccittini", "team": "Barcelona", "minute": 64, "xg": 0.04339203, "goal": 1, "is_pen": false}, {"season": "2018/2019", "match_id": 16086, "player": "Marc Roca Junqu\u00e9", "team": "Espanyol", "minute": 66, "xg": 0.006765969, "goal": 0, "is_pen": false}, {"season": "2018/2019", "match_id": 16086, "player": "Borja Iglesias Quintas", "team": "Espanyol", "minute": 67, "xg": 0.24073598, "goal": 0, "is_pen": false}, {"season": "2018/2019", "match_id": 16086, "player": "Philippe Coutinho Correia", "team": "Barcelona", "minute": 68, "xg": 0.050434124, "goal": 0, "is_pen": false}, {"season": "2018/2019", "match_id": 16086, "player": "Lionel Andr\u00e9s Messi Cuccittini", "team": "Barcelona", "minute": 68, "xg": 0.38777235, "goal": 0, "is_pen": false}, {"season": "2018/2019", "match_id": 16086, "player": "Ivan Rakiti\u0107", "team": "Barcelona", "minute": 79, "xg": 0.022416975, "goal": 0, "is_pen": false}, {"season": "2018/2019", "match_id": 16086, "player": "V\u00edctor S\u00e1nchez Mata", "team": "Espanyol", "minute": 80, "xg": 0.07251559, "goal": 0, "is_pen": false}, {"season": "2018/2019", "match_id": 16086, "player": "Leonardo Carrilho Baptist\u00e3o", "team": "Espanyol", "minute": 84, "xg": 0.031098267, "goal": 0, "is_pen": false}, {"season": "2018/2019", "match_id": 16086, "player": "Borja Iglesias Quintas", "team": "Espanyol", "minute": 90, "xg": 0.08047921, "goal": 0, "is_pen": false}, {"season": "2018/2019", "match_id": 16086, "player": "D\u00eddac Vil\u00e1 Rossell\u00f3", "team": "Espanyol", "minute": 90, "xg": 0.07438837, "goal": 0, "is_pen": false}, {"season": "2018/2019", "match_id": 16086, "player": "Munir El Haddadi Mohamed", "team": "Barcelona", "minute": 94, "xg": 0.09655675, "goal": 0, "is_pen": false}]