[{"season": "2013/2014", "match_id": 265857, "player": "Neymar da Silva Santos Junior", "team": "Barcelona", "minute": 3, "xg": 0.0587618, "goal": 0, "is_pen": false}, {"season": "2013/2014", "match_id": 265857, "player": "Karim Benzema", "team": "Real Madrid", "minute": 4, "xg": 0.095666684, "goal": 0, "is_pen": false}, {"season": "2013/2014", "match_id": 265857, "player": "Andr\u00e9s Iniesta Luj\u00e1n", "team": "Barcelona", "minute": 6, "xg": 0.1604232, "goal": 1, "is_pen": false}, {"season": "2013/2014", "match_id": 265857, "player": "Karim Benzema", "team": "Real Madrid", "minute": 11, "xg": 0.04239128, "goal": 0, "is_pen": false}, {"season": "2013/2014", "match_id": 265857, "player": "Karim Benzema", "team": "Real Madrid", "minute": 12, "xg": 0.21859588, "goal": 0, "is_pen": false}, {"season": "2013/2014", "match_id": 265857, "player": "Lionel Andr\u00e9s Messi Cuccittini", "team": "Barcelona", "minute": 14, "xg": 0.10783732, "goal": 0, "is_pen": false}, {"season": "2013/2014", "match_id": 265857, "player": "Cristiano Ronaldo dos Santos Aveiro", "team": "Real Madrid", "minute": 17, "xg": 0.021814093, "goal": 0, "is_pen": false}, {"season": "2013/2014", "match_id": 265857, "player": "Neymar da Silva Santos Junior", "team": "Barcelona", "minute": 18, "xg": 0.13398187, "goal": 0, "is_pen": false}, {"season": "2013/2014", "match_id": 265857, "player": "Karim Benzema", "team": "Real Madrid", "minute": 19, "xg": 0.1251444, "goal": 1, "is_pen": false}, {"season": "2013/2014", "match_id": 265857, "player": "Karim Benzema", "team": "Real Madrid", "minute": 23, "xg": 0.21502556, "goal": 1, "is_pen": false}, {"season": "2013/2014", "match_id": 265857, "player": "Lionel Andr\u00e9s Messi Cuccittini", "team": "Barcelona", "minute": 25, "xg": 0.04030618, "goal": 0, "is_pen": false}, {"season": "2013/2014", "match_id": 265857, "player": "Karim Benzema", "team": "Real Madrid", "minute": 25, "xg": 0.10746595, "goal": 0, "is_pen": false}, {"season": "2013/2014", "match_id": 265857, "player": "Cristiano Ronaldo dos Santos Aveiro", "team": "Real Madrid", "minute": 26, "xg": 0.0742228, "goal": 0, "is_pen": false}, {"season": "2013/2014", "match_id": 265857, "player": "Luka Modri\u0107", "team": "Real Madrid", "minute": 26, "xg": 0.052870486, "goal": 0, "is_pen": false}, {"season": "2013/2014", "match_id": 265857, "player": "Xavier Hern\u00e1ndez Creus", "team": "Barcelona", "minute": 29, "xg": 0.027443403, "goal": 0, "is_pen": false}, {"season": "2013/2014", "match_id": 265857, "player": "Gerard Piqu\u00e9 Bernab\u00e9u", "team": "Barcelona", "minute": 39, "xg": 0.06263564, "goal": 0, "is_pen": false}, {"season": "2013/2014", "match_id": 265857, "player": "Lionel Andr\u00e9s Messi Cuccittini", "team": "Barcelona", "minute": 41, "xg": 0.08744124, "goal": 1, "is_pen": false}, {"season": "2013/2014", "match_id": 265857, "player": "Karim Benzema", "team": "Real Madrid", "minute": 45, "xg": 0.09393917, "goal": 0, "is_pen": false}, {"season": "2013/2014", "match_id": 265857, "player": "Karim Benzema", "team": "Real Madrid", "minute": 51, "xg": 0.26502767, "goal": 0, "is_pen": false}, {"season": "2013/2014", "match_id": 265857, "player": "Cristiano Ronaldo dos Santos Aveiro", "team": "Real Madrid", "minute": 54, "xg": 0.7835, "goal": 1, "is_pen": true}, {"season": "2013/2014", "match_id": 265857, "player": "Gareth Frank Bale", "team": "Real Madrid", "minute": 57, "xg": 0.10100515, "goal": 0, "is_pen": false}, {"season": "2013/2014", "match_id": 265857, "player": "Andr\u00e9s Iniesta Luj\u00e1n", "team": "Barcelona", "minute": 59, "xg": 0.019769676, "goal": 0, "is_pen": false}, {"season": "2013/2014", "match_id": 265857, "player": "Neymar da Silva Santos Junior", "team": "Barcelona", "minute": 60, "xg": 0.025534632, "goal": 0, "is_pen": false}, {"season": "2013/2014", "match_id": 265857, "player": "Lionel Andr\u00e9s Messi Cuccittini", "team": "Barcelona", "minute": 64, "xg": 0.7835, "goal": 1, "is_pen": true}, {"season": "2013/2014", "match_id": 265857, "player": "Andr\u00e9s Iniesta Luj\u00e1n", "team": "Barcelona", "minute": 67, "xg": 0.024557572, "goal": 0, "is_pen": false}, {"season": "2013/2014", "match_id": 265857, "player": "Sergio Busquets i Burgos", "team": "Barcelona", "minute": 71, "xg": 0.06496262, "goal": 0, "is_pen": false}, {"season": "2013/2014", "match_id": 265857, "player": "Lionel Andr\u00e9s Messi Cuccittini", "team": "Barcelona", "minute": 72, "xg": 0.051266633, "goal": 0, "is_pen": false}, {"season": "2013/2014", "match_id": 265857, "player": "Daniel Alves da Silva", "team": "Barcelona", "minute": 73, "xg": 0.025510024, "goal": 0, "is_pen": false}, {"season": "2013/2014", "match_id": 265857, "player": "Javier Alejandro Mascherano", "team": "Barcelona", "minute": 81, "xg": 0.014068461, "goal": 0, "is_pen": false}, {"season": "2013/2014", "match_id": 265857, "player": "Lionel Andr\u00e9s Messi Cuccittini", "team": "Barcelona", "minute": 83, "xg": 0.7835, "goal": 1, "is_pen": true}, {"season": "2013/2014", "match_id": 265857, "player": "Alexis Alejandro S\u00e1nchez S\u00e1nchez", "team": "Barcelona", "minute": 92, "xg": 0.058252055, "goal": 0, "is_pen": false}]