[{"season": "2020/2021", "match_id": 3764440, "player": "Francisco Ant\u00f3nio Machado Mota de Castro Trinc\u00e3o", "team": "Barcelona", "minute": 1, "xg": 0.06967228, "goal": 0, "is_pen": false}, {"season": "2020/2021", "match_id": 3764440, "player": "Lucas Ariel Boy\u00e9", "team": "Elche", "minute": 4, "xg": 0.298439, "goal": 0, "is_pen": false}, {"season": "2020/2021", "match_id": 3764440, "player": "Francisco Ant\u00f3nio Machado Mota de Castro Trinc\u00e3o", "team": "Barcelona", "minute": 19, "xg": 0.50473726, "goal": 0, "is_pen": false}, {"season": "2020/2021", "match_id": 3764440, "player": "Jos\u00e9 Ra\u00fal Guti\u00e9rrez Parejo", "team": "Elche", "minute": 32, "xg": 0.007819599, "goal": 0, "is_pen": false}, {"season": "2020/2021", "match_id": 3764440, "player": "Pere Milla Pe\u00f1a", "team": "Elche", "minute": 43, "xg": 0.07418988, "goal": 0, "is_pen": false}, {"season": "2020/2021", "match_id": 3764440, "player": "Lionel Andr\u00e9s Messi Cuccittini", "team": "Barcelona", "minute": 47, "xg": 0.3347203, "goal": 1, "is_pen": false}, {"season": "2020/2021", "match_id": 3764440, "player": "Lucas Ariel Boy\u00e9", "team": "Elche", "minute": 49, "xg": 0.095620655, "goal": 0, "is_pen": false}, {"season": "2020/2021", "match_id": 3764440, "player": "Lionel Andr\u00e9s Messi Cuccittini", "team": "Barcelona", "minute": 50, "xg": 0.07844107, "goal": 0, "is_pen": false}, {"season": "2020/2021", "match_id": 3764440, "player": "Ousmane Demb\u00e9l\u00e9", "team": "Barcelona", "minute": 63, "xg": 0.04752228, "goal": 0, "is_pen": false}, {"season": "2020/2021", "match_id": 3764440, "player": "Lionel Andr\u00e9s Messi Cuccittini", "team": "Barcelona", "minute": 68, "xg": 0.57921857, "goal": 1, "is_pen": false}, {"season": "2020/2021", "match_id": 3764440, "player": "Jordi Alba Ramos", "team": "Barcelona", "minute": 72, "xg": 0.42237553, "goal": 1, "is_pen": false}, {"season": "2020/2021", "match_id": 3764440, "player": "Guido Marcelo Carrillo", "team": "Elche", "minute": 74, "xg": 0.09103747, "goal": 0, "is_pen": false}, {"season": "2020/2021", "match_id": 3764440, "player": "Antoine Griezmann", "team": "Barcelona", "minute": 81, "xg": 0.57339495, "goal": 0, "is_pen": false}, {"season": "2020/2021", "match_id": 3764440, "player": "Guido Marcelo Carrillo", "team": "Elche", "minute": 90, "xg": 0.10336546, "goal": 0, "is_pen": false}, {"season": "2020/2021", "match_id": 3764440, "player": "Ousmane Demb\u00e9l\u00e9", "team": "Barcelona", "minute": 92, "xg": 0.09100202, "goal": 0, "is_pen": false}]