[{"season": "2015/2016", "match_id": 3825741, "player": "Carlos Carmona Bonet", "team": "Sporting Gij\u00f3n", "minute": 0, "xg": 0.91363096, "goal": 1, "is_pen": false}, {"season": "2015/2016", "match_id": 3825741, "player": "Daniel Arnaud N''Di\t", "team": "Sporting Gij\u00f3n", "minute": 8, "xg": 0.60172373, "goal": 1, "is_pen": false}, {"season": "2015/2016", "match_id": 3825741, "player": "Rachid A\u00eft-Atmane", "team": "Sporting Gij\u00f3n", "minute": 18, "xg": 0.018552186, "goal": 0, "is_pen": false}, {"season": "2015/2016", "match_id": 3825741, "player": "Carlos Carmona Bonet", "team": "Sporting Gij\u00f3n", "minute": 21, "xg": 0.017747993, "goal": 0, "is_pen": false}, {"season": "2015/2016", "match_id": 3825741, "player": "Carlos Alberto Vela Garrido", "team": "Real Sociedad", "minute": 27, "xg": 0.07424728, "goal": 0, "is_pen": false}, {"season": "2015/2016", "match_id": 3825741, "player": "Aritz Elustondo Irribaria", "team": "Real Sociedad", "minute": 36, "xg": 0.34304538, "goal": 0, "is_pen": false}, {"season": "2015/2016", "match_id": 3825741, "player": "Carlos Alberto Vela Garrido", "team": "Real Sociedad", "minute": 36, "xg": 0.058934465, "goal": 1, "is_pen": false}, {"season": "2015/2016", "match_id": 3825741, "player": "Arnaldo Antonio Sanabria Ayala", "team": "Sporting Gij\u00f3n", "minute": 43, "xg": 0.7281325, "goal": 1, "is_pen": false}, {"season": "2015/2016", "match_id": 3825741, "player": "Arnaldo Antonio Sanabria Ayala", "team": "Sporting Gij\u00f3n", "minute": 46, "xg": 0.635523, "goal": 0, "is_pen": false}, {"season": "2015/2016", "match_id": 3825741, "player": "Jonathas Cristian de Jesus", "team": "Real Sociedad", "minute": 48, "xg": 0.33118486, "goal": 0, "is_pen": false}, {"season": "2015/2016", "match_id": 3825741, "player": "Carlos Alberto Vela Garrido", "team": "Real Sociedad", "minute": 48, "xg": 0.27063516, "goal": 0, "is_pen": false}, {"season": "2015/2016", "match_id": 3825741, "player": "Carlos Carmona Bonet", "team": "Sporting Gij\u00f3n", "minute": 52, "xg": 0.4191369, "goal": 0, "is_pen": false}, {"season": "2015/2016", "match_id": 3825741, "player": "Arnaldo Antonio Sanabria Ayala", "team": "Sporting Gij\u00f3n", "minute": 52, "xg": 0.8862195, "goal": 1, "is_pen": false}, {"season": "2015/2016", "match_id": 3825741, "player": "H\u00e9ctor Hern\u00e1ndez Ortega", "team": "Real Sociedad", "minute": 54, "xg": 0.08624858, "goal": 0, "is_pen": false}, {"season": "2015/2016", "match_id": 3825741, "player": "Asier Illarramendi Andonegi", "team": "Real Sociedad", "minute": 60, "xg": 0.046609487, "goal": 0, "is_pen": false}, {"season": "2015/2016", "match_id": 3825741, "player": "Ismael L\u00f3pez Blanco", "team": "Sporting Gij\u00f3n", "minute": 67, "xg": 0.028283432, "goal": 0, "is_pen": false}, {"season": "2015/2016", "match_id": 3825741, "player": "Jonathas Cristian de Jesus", "team": "Real Sociedad", "minute": 69, "xg": 0.029539159, "goal": 0, "is_pen": false}, {"season": "2015/2016", "match_id": 3825741, "player": "Rachid A\u00eft-Atmane", "team": "Sporting Gij\u00f3n", "minute": 77, "xg": 0.09329134, "goal": 0, "is_pen": false}, {"season": "2015/2016", "match_id": 3825741, "player": "Arnaldo Antonio Sanabria Ayala", "team": "Sporting Gij\u00f3n", "minute": 80, "xg": 0.19543105, "goal": 1, "is_pen": false}, {"season": "2015/2016", "match_id": 3825741, "player": "Jonathas Cristian de Jesus", "team": "Real Sociedad", "minute": 86, "xg": 0.08417055, "goal": 0, "is_pen": false}, {"season": "2015/2016", "match_id": 3825741, "player": "Carlos Carmona Bonet", "team": "Sporting Gij\u00f3n", "minute": 87, "xg": 0.0050012353, "goal": 0, "is_pen": false}, {"season": "2015/2016", "match_id": 3825741, "player": "Arnaldo Antonio Sanabria Ayala", "team": "Sporting Gij\u00f3n", "minute": 91, "xg": 0.13321018, "goal": 0, "is_pen": false}]