[{"season": "2015/2016", "match_id": 3825705, "player": "Daniel Garc\u00eda Carrillo", "team": "Eibar", "minute": 3, "xg": 0.0068552895, "goal": 0, "is_pen": false}, {"season": "2015/2016", "match_id": 3825705, "player": "Iv\u00e1n Ramis Barrios", "team": "Eibar", "minute": 7, "xg": 0.030346448, "goal": 0, "is_pen": false}, {"season": "2015/2016", "match_id": 3825705, "player": "Sergio Gont\u00e1n Gallardo", "team": "Eibar", "minute": 11, "xg": 0.008368317, "goal": 0, "is_pen": false}, {"season": "2015/2016", "match_id": 3825705, "player": "Daniel Garc\u00eda Carrillo", "team": "Eibar", "minute": 13, "xg": 0.031349935, "goal": 0, "is_pen": false}, {"season": "2015/2016", "match_id": 3825705, "player": "Sa\u00fal Berj\u00f3n P\u00e9rez", "team": "Eibar", "minute": 20, "xg": 0.0084888665, "goal": 0, "is_pen": false}, {"season": "2015/2016", "match_id": 3825705, "player": "Alen Halilovi\u0107", "team": "Sporting Gij\u00f3n", "minute": 23, "xg": 0.14678799, "goal": 0, "is_pen": false}, {"season": "2015/2016", "match_id": 3825705, "player": "Sa\u00fal Berj\u00f3n P\u00e9rez", "team": "Eibar", "minute": 29, "xg": 0.07957967, "goal": 0, "is_pen": false}, {"season": "2015/2016", "match_id": 3825705, "player": "Borja Gonz\u00e1lez Tom\u00e1s", "team": "Eibar", "minute": 31, "xg": 0.030234497, "goal": 0, "is_pen": false}, {"season": "2015/2016", "match_id": 3825705, "player": "Sergio Gont\u00e1n Gallardo", "team": "Eibar", "minute": 37, "xg": 0.023106523, "goal": 0, "is_pen": false}, {"season": "2015/2016", "match_id": 3825705, "player": "Gonzalo Escalante", "team": "Eibar", "minute": 38, "xg": 0.07171882, "goal": 0, "is_pen": false}, {"season": "2015/2016", "match_id": 3825705, "player": "Sa\u00fal Berj\u00f3n P\u00e9rez", "team": "Eibar", "minute": 42, "xg": 0.025184186, "goal": 0, "is_pen": false}, {"season": "2015/2016", "match_id": 3825705, "player": "Jonathan Rodr\u00edguez Men\u00e9ndez", "team": "Sporting Gij\u00f3n", "minute": 46, "xg": 0.03450606, "goal": 0, "is_pen": false}, {"season": "2015/2016", "match_id": 3825705, "player": "Sergio Gont\u00e1n Gallardo", "team": "Eibar", "minute": 54, "xg": 0.1057515, "goal": 1, "is_pen": false}, {"season": "2015/2016", "match_id": 3825705, "player": "Borja Gonz\u00e1lez Tom\u00e1s", "team": "Eibar", "minute": 61, "xg": 0.5711374, "goal": 1, "is_pen": false}, {"season": "2015/2016", "match_id": 3825705, "player": "Sa\u00fal Berj\u00f3n P\u00e9rez", "team": "Eibar", "minute": 63, "xg": 0.070781566, "goal": 0, "is_pen": false}, {"season": "2015/2016", "match_id": 3825705, "player": "Simone Verdi", "team": "Eibar", "minute": 71, "xg": 0.0061756056, "goal": 0, "is_pen": false}, {"season": "2015/2016", "match_id": 3825705, "player": "Carlos Castro Garc\u00eda", "team": "Sporting Gij\u00f3n", "minute": 74, "xg": 0.058361705, "goal": 0, "is_pen": false}, {"season": "2015/2016", "match_id": 3825705, "player": "Sergio Gont\u00e1n Gallardo", "team": "Eibar", "minute": 76, "xg": 0.05304387, "goal": 0, "is_pen": false}, {"season": "2015/2016", "match_id": 3825705, "player": "Daniel Arnaud N''Di\t", "team": "Sporting Gij\u00f3n", "minute": 80, "xg": 0.093680695, "goal": 0, "is_pen": false}, {"season": "2015/2016", "match_id": 3825705, "player": "Jorge Mer\u00e9 P\u00e9rez", "team": "Sporting Gij\u00f3n", "minute": 82, "xg": 0.0741954, "goal": 0, "is_pen": false}, {"season": "2015/2016", "match_id": 3825705, "player": "Alen Halilovi\u0107", "team": "Sporting Gij\u00f3n", "minute": 85, "xg": 0.06425996, "goal": 0, "is_pen": false}]