[{"season": "2005/2006", "match_id": 68320, "player": "Anderson Lu\u00eds de Souza", "team": "Barcelona", "minute": 1, "xg": 0.078868814, "goal": 0, "is_pen": false}, {"season": "2005/2006", "match_id": 68320, "player": "Thiago Motta", "team": "Barcelona", "minute": 6, "xg": 0.005388816, "goal": 0, "is_pen": false}, {"season": "2005/2006", "match_id": 68320, "player": "Jos\u00e9 Joaqu\u00edn Moreno Verd\u00fa", "team": "Villarreal", "minute": 7, "xg": 0.12948102, "goal": 0, "is_pen": false}, {"season": "2005/2006", "match_id": 68320, "player": "Jos\u00e9 Joaqu\u00edn Moreno Verd\u00fa", "team": "Villarreal", "minute": 13, "xg": 0.056458678, "goal": 0, "is_pen": false}, {"season": "2005/2006", "match_id": 68320, "player": "Ronaldo de Assis Moreira", "team": "Barcelona", "minute": 18, "xg": 0.015063839, "goal": 0, "is_pen": false}, {"season": "2005/2006", "match_id": 68320, "player": "Lionel Andr\u00e9s Messi Cuccittini", "team": "Barcelona", "minute": 18, "xg": 0.06338402, "goal": 0, "is_pen": false}, {"season": "2005/2006", "match_id": 68320, "player": "Ronaldo de Assis Moreira", "team": "Barcelona", "minute": 23, "xg": 0.0064550075, "goal": 0, "is_pen": false}, {"season": "2005/2006", "match_id": 68320, "player": "Juan Rom\u00e1n Riquelme", "team": "Villarreal", "minute": 24, "xg": 0.023416335, "goal": 0, "is_pen": false}, {"season": "2005/2006", "match_id": 68320, "player": "Ronaldo de Assis Moreira", "team": "Barcelona", "minute": 29, "xg": 0.0073010568, "goal": 0, "is_pen": false}, {"season": "2005/2006", "match_id": 68320, "player": "Samuel Eto''o Fils", "team": "Barcelona", "minute": 52, "xg": 0.025284246, "goal": 0, "is_pen": false}, {"season": "2005/2006", "match_id": 68320, "player": "Ronaldo de Assis Moreira", "team": "Barcelona", "minute": 60, "xg": 0.056663714, "goal": 0, "is_pen": false}, {"season": "2005/2006", "match_id": 68320, "player": "Oleguer Presas Renom", "team": "Barcelona", "minute": 60, "xg": 0.016689016, "goal": 0, "is_pen": false}, {"season": "2005/2006", "match_id": 68320, "player": "Anderson Lu\u00eds de Souza", "team": "Barcelona", "minute": 62, "xg": 0.026054524, "goal": 1, "is_pen": false}, {"season": "2005/2006", "match_id": 68320, "player": "Lionel Andr\u00e9s Messi Cuccittini", "team": "Barcelona", "minute": 65, "xg": 0.06803406, "goal": 0, "is_pen": false}, {"season": "2005/2006", "match_id": 68320, "player": "Jos\u00e9 Mar\u00eda Romero Poy\u00f3n", "team": "Villarreal", "minute": 71, "xg": 0.12627707, "goal": 0, "is_pen": false}, {"season": "2005/2006", "match_id": 68320, "player": "Juan Rom\u00e1n Riquelme", "team": "Villarreal", "minute": 89, "xg": 0.032207396, "goal": 0, "is_pen": false}, {"season": "2005/2006", "match_id": 68320, "player": "Roger Garc\u00eda Junyent", "team": "Villarreal", "minute": 93, "xg": 0.02405268, "goal": 0, "is_pen": false}]