[{"season": "2006/2007", "match_id": 69159, "player": "Andr\u00e9s Iniesta Luj\u00e1n", "team": "Barcelona", "minute": 7, "xg": 0.045503426, "goal": 0, "is_pen": false}, {"season": "2006/2007", "match_id": 69159, "player": "Ludovic Giuly", "team": "Barcelona", "minute": 8, "xg": 0.04063711, "goal": 0, "is_pen": false}, {"season": "2006/2007", "match_id": 69159, "player": "Samuel Eto''o Fils", "team": "Barcelona", "minute": 10, "xg": 0.006450135, "goal": 0, "is_pen": false}, {"season": "2006/2007", "match_id": 69159, "player": "Rafael M\u00e1rquez \u00c1lvarez", "team": "Barcelona", "minute": 13, "xg": 0.15841584, "goal": 0, "is_pen": false}, {"season": "2006/2007", "match_id": 69159, "player": "Giovanni van Bronckhorst", "team": "Barcelona", "minute": 25, "xg": 0.019290563, "goal": 0, "is_pen": false}, {"season": "2006/2007", "match_id": 69159, "player": "Samuel Eto''o Fils", "team": "Barcelona", "minute": 25, "xg": 0.106861725, "goal": 0, "is_pen": false}, {"season": "2006/2007", "match_id": 69159, "player": "Anderson Lu\u00eds de Souza", "team": "Barcelona", "minute": 27, "xg": 0.020739593, "goal": 0, "is_pen": false}, {"season": "2006/2007", "match_id": 69159, "player": "Jon\u00e1s Manuel Guti\u00e9rrez", "team": "Mallorca", "minute": 30, "xg": 0.7835, "goal": 0, "is_pen": true}, {"season": "2006/2007", "match_id": 69159, "player": "Lionel Andr\u00e9s Messi Cuccittini", "team": "Barcelona", "minute": 31, "xg": 0.0074054915, "goal": 0, "is_pen": false}, {"season": "2006/2007", "match_id": 69159, "player": "Anderson Lu\u00eds de Souza", "team": "Barcelona", "minute": 35, "xg": 0.040999018, "goal": 0, "is_pen": false}, {"season": "2006/2007", "match_id": 69159, "player": "Ludovic Giuly", "team": "Barcelona", "minute": 39, "xg": 0.016107408, "goal": 0, "is_pen": false}, {"season": "2006/2007", "match_id": 69159, "player": "Jon\u00e1s Manuel Guti\u00e9rrez", "team": "Mallorca", "minute": 40, "xg": 0.036434904, "goal": 0, "is_pen": false}, {"season": "2006/2007", "match_id": 69159, "player": "Fernando Navarro i Corbacho", "team": "Mallorca", "minute": 44, "xg": 0.008893381, "goal": 0, "is_pen": false}, {"season": "2006/2007", "match_id": 69159, "player": "Anderson Lu\u00eds de Souza", "team": "Barcelona", "minute": 46, "xg": 0.066121325, "goal": 0, "is_pen": false}, {"season": "2006/2007", "match_id": 69159, "player": "Lionel Andr\u00e9s Messi Cuccittini", "team": "Barcelona", "minute": 47, "xg": 0.07690114, "goal": 0, "is_pen": false}, {"season": "2006/2007", "match_id": 69159, "player": "Carles Puyol i Saforcada", "team": "Barcelona", "minute": 54, "xg": 0.0854674, "goal": 0, "is_pen": false}, {"season": "2006/2007", "match_id": 69159, "player": "Gianluca Zambrotta", "team": "Barcelona", "minute": 59, "xg": 0.009108402, "goal": 0, "is_pen": false}, {"season": "2006/2007", "match_id": 69159, "player": "Anderson Lu\u00eds de Souza", "team": "Barcelona", "minute": 63, "xg": 0.042153224, "goal": 0, "is_pen": false}, {"season": "2006/2007", "match_id": 69159, "player": "Giovanni van Bronckhorst", "team": "Barcelona", "minute": 64, "xg": 0.08448665, "goal": 0, "is_pen": false}, {"season": "2006/2007", "match_id": 69159, "player": "Javier Pedro Saviola Fern\u00e1ndez", "team": "Barcelona", "minute": 66, "xg": 0.36651027, "goal": 0, "is_pen": false}, {"season": "2006/2007", "match_id": 69159, "player": "Ariel Miguel Santiago Ibagaza", "team": "Mallorca", "minute": 73, "xg": 0.03354725, "goal": 0, "is_pen": false}, {"season": "2006/2007", "match_id": 69159, "player": "Giovanni van Bronckhorst", "team": "Barcelona", "minute": 78, "xg": 0.0373833, "goal": 0, "is_pen": false}, {"season": "2006/2007", "match_id": 69159, "player": "Giovanni van Bronckhorst", "team": "Barcelona", "minute": 79, "xg": 0.036034245, "goal": 0, "is_pen": false}, {"season": "2006/2007", "match_id": 69159, "player": "Juliano Haus Belletti", "team": "Barcelona", "minute": 81, "xg": 0.019270742, "goal": 0, "is_pen": false}, {"season": "2006/2007", "match_id": 69159, "player": "Lionel Andr\u00e9s Messi Cuccittini", "team": "Barcelona", "minute": 83, "xg": 0.06799393, "goal": 0, "is_pen": false}, {"season": "2006/2007", "match_id": 69159, "player": "Giovanni van Bronckhorst", "team": "Barcelona", "minute": 85, "xg": 0.01618726, "goal": 0, "is_pen": false}, {"season": "2006/2007", "match_id": 69159, "player": "Rafael M\u00e1rquez \u00c1lvarez", "team": "Barcelona", "minute": 88, "xg": 0.08376675, "goal": 0, "is_pen": false}, {"season": "2006/2007", "match_id": 69159, "player": "Javier Pedro Saviola Fern\u00e1ndez", "team": "Barcelona", "minute": 88, "xg": 0.45983338, "goal": 0, "is_pen": false}]