[{"season": "2008/2009", "match_id": 69225, "player": "Eric-Sylvain Bilal Abidal", "team": "Barcelona", "minute": 1, "xg": 0.007064939, "goal": 0, "is_pen": false}, {"season": "2008/2009", "match_id": 69225, "player": "Lionel Andr\u00e9s Messi Cuccittini", "team": "Barcelona", "minute": 5, "xg": 0.07295281, "goal": 0, "is_pen": false}, {"season": "2008/2009", "match_id": 69225, "player": "Thierry Henry", "team": "Barcelona", "minute": 6, "xg": 0.015879327, "goal": 0, "is_pen": false}, {"season": "2008/2009", "match_id": 69225, "player": "Lionel Andr\u00e9s Messi Cuccittini", "team": "Barcelona", "minute": 15, "xg": 0.040939737, "goal": 0, "is_pen": false}, {"season": "2008/2009", "match_id": 69225, "player": "Gn\u00e9gn\u00e9ri Yaya Tour\u00e9", "team": "Barcelona", "minute": 16, "xg": 0.10128594, "goal": 0, "is_pen": false}, {"season": "2008/2009", "match_id": 69225, "player": "Eric-Sylvain Bilal Abidal", "team": "Barcelona", "minute": 18, "xg": 0.236183, "goal": 0, "is_pen": false}, {"season": "2008/2009", "match_id": 69225, "player": "Daniel Alves da Silva", "team": "Barcelona", "minute": 22, "xg": 0.007017402, "goal": 0, "is_pen": false}, {"season": "2008/2009", "match_id": 69225, "player": "Wesley Sneijder", "team": "Real Madrid", "minute": 23, "xg": 0.06679663, "goal": 0, "is_pen": false}, {"season": "2008/2009", "match_id": 69225, "player": "Royston Ricky Drenthe", "team": "Real Madrid", "minute": 25, "xg": 0.22765219, "goal": 0, "is_pen": false}, {"season": "2008/2009", "match_id": 69225, "player": "Gonzalo Gerardo Higua\u00edn", "team": "Real Madrid", "minute": 26, "xg": 0.04843094, "goal": 0, "is_pen": false}, {"season": "2008/2009", "match_id": 69225, "player": "Thierry Henry", "team": "Barcelona", "minute": 32, "xg": 0.008805739, "goal": 0, "is_pen": false}, {"season": "2008/2009", "match_id": 69225, "player": "Samuel Eto''o Fils", "team": "Barcelona", "minute": 32, "xg": 0.01754488, "goal": 0, "is_pen": false}, {"season": "2008/2009", "match_id": 69225, "player": "Samuel Eto''o Fils", "team": "Barcelona", "minute": 44, "xg": 0.05749554, "goal": 0, "is_pen": false}, {"season": "2008/2009", "match_id": 69225, "player": "Samuel Eto''o Fils", "team": "Barcelona", "minute": 47, "xg": 0.04238002, "goal": 0, "is_pen": false}, {"season": "2008/2009", "match_id": 69225, "player": "Ra\u00fal Gonz\u00e1lez Blanco", "team": "Real Madrid", "minute": 49, "xg": 0.06705482, "goal": 0, "is_pen": false}, {"season": "2008/2009", "match_id": 69225, "player": "Lionel Andr\u00e9s Messi Cuccittini", "team": "Barcelona", "minute": 51, "xg": 0.025395785, "goal": 0, "is_pen": false}, {"season": "2008/2009", "match_id": 69225, "player": "Samuel Eto''o Fils", "team": "Barcelona", "minute": 55, "xg": 0.008393286, "goal": 0, "is_pen": false}, {"season": "2008/2009", "match_id": 69225, "player": "Samuel Eto''o Fils", "team": "Barcelona", "minute": 66, "xg": 0.3547855, "goal": 0, "is_pen": false}, {"season": "2008/2009", "match_id": 69225, "player": "Lionel Andr\u00e9s Messi Cuccittini", "team": "Barcelona", "minute": 67, "xg": 0.01735703, "goal": 0, "is_pen": false}, {"season": "2008/2009", "match_id": 69225, "player": "Xavier Hern\u00e1ndez Creus", "team": "Barcelona", "minute": 68, "xg": 0.03471091, "goal": 0, "is_pen": false}, {"season": "2008/2009", "match_id": 69225, "player": "Samuel Eto''o Fils", "team": "Barcelona", "minute": 69, "xg": 0.7835, "goal": 0, "is_pen": true}, {"season": "2008/2009", "match_id": 69225, "player": "Samuel Eto''o Fils", "team": "Barcelona", "minute": 71, "xg": 0.07200621, "goal": 0, "is_pen": false}, {"season": "2008/2009", "match_id": 69225, "player": "Daniel Alves da Silva", "team": "Barcelona", "minute": 73, "xg": 0.027329626, "goal": 0, "is_pen": false}, {"season": "2008/2009", "match_id": 69225, "player": "Miguel Palanca Fern\u00e1ndez", "team": "Real Madrid", "minute": 77, "xg": 0.04119722, "goal": 0, "is_pen": false}, {"season": "2008/2009", "match_id": 69225, "player": "Samuel Eto''o Fils", "team": "Barcelona", "minute": 82, "xg": 0.5656256, "goal": 1, "is_pen": false}, {"season": "2008/2009", "match_id": 69225, "player": "Fernando Rub\u00e9n Gago", "team": "Real Madrid", "minute": 84, "xg": 0.01744967, "goal": 0, "is_pen": false}, {"season": "2008/2009", "match_id": 69225, "player": "Lionel Andr\u00e9s Messi Cuccittini", "team": "Barcelona", "minute": 91, "xg": 0.17463343, "goal": 1, "is_pen": false}]